flowery/__init__.py
flowery/image.py
flowery/py.typed
flowery/typing.py
flowery/utils.py
flowery-0.0.1.dist-info/WHEEL
flowery-0.0.1.dist-info/METADATA
flowery-0.0.1.dist-info/licenses/LICENSE
flowery-0.0.1.dist-info/RECORD
