Metadata-Version: 2.1
Name: flowery
Version: 0.0.1
Summary: 💐 Python image processing library focusing on drawing
License: MIT
Author-email: Akirami <akiramiaya@outlook.com>
Requires-Python: >=3.10,<4.0
Requires-Dist: pillow<10.0.0,>=9.5.0
Requires-Dist: typing-extensions>=4.5.0
Project-URL: repository, https://github.com/A-kirami/flowery
